scrapy/VERSION
scrapy/__init__.py
scrapy/__main__.py
scrapy/addons.py
scrapy/cmdline.py
scrapy/crawler.py
scrapy/dupefilters.py
scrapy/exceptions.py
scrapy/exporters.py
scrapy/extension.py
scrapy/interfaces.py
scrapy/item.py
scrapy/link.py
scrapy/logformatter.py
scrapy/mail.py
scrapy/middleware.py
scrapy/mime.types
scrapy/pqueues.py
scrapy/py.typed
scrapy/resolver.py
scrapy/responsetypes.py
scrapy/robotstxt.py
scrapy/shell.py
scrapy/signalmanager.py
scrapy/signals.py
scrapy/spiderloader.py
scrapy/squeues.py
scrapy/statscollectors.py
scrapy/commands/__init__.py
scrapy/commands/bench.py
scrapy/commands/check.py
scrapy/commands/crawl.py
scrapy/commands/edit.py
scrapy/commands/fetch.py
scrapy/commands/genspider.py
scrapy/commands/list.py
scrapy/commands/parse.py
scrapy/commands/runspider.py
scrapy/commands/settings.py
scrapy/commands/shell.py
scrapy/commands/startproject.py
scrapy/commands/version.py
scrapy/commands/view.py
scrapy/contracts/__init__.py
scrapy/contracts/default.py
scrapy/core/__init__.py
scrapy/core/engine.py
scrapy/core/scheduler.py
scrapy/core/scraper.py
scrapy/core/spidermw.py
scrapy/core/downloader/__init__.py
scrapy/core/downloader/contextfactory.py
scrapy/core/downloader/middleware.py
scrapy/core/downloader/tls.py
scrapy/core/downloader/webclient.py
scrapy/core/downloader/handlers/__init__.py
scrapy/core/downloader/handlers/datauri.py
scrapy/core/downloader/handlers/file.py
scrapy/core/downloader/handlers/ftp.py
scrapy/core/downloader/handlers/http.py
scrapy/core/downloader/handlers/http10.py
scrapy/core/downloader/handlers/http11.py
scrapy/core/downloader/handlers/http2.py
scrapy/core/downloader/handlers/s3.py
scrapy/core/http2/__init__.py
scrapy/core/http2/agent.py
scrapy/core/http2/protocol.py
scrapy/core/http2/stream.py
scrapy/downloadermiddlewares/__init__.py
scrapy/downloadermiddlewares/ajaxcrawl.py
scrapy/downloadermiddlewares/cookies.py
scrapy/downloadermiddlewares/defaultheaders.py
scrapy/downloadermiddlewares/downloadtimeout.py
new_python_scrapy-0.1.3.dist-info/AUTHORS
new_python_scrapy-0.1.3.dist-info/LICENSE
new_python_scrapy-0.1.3.dist-info/METADATA
new_python_scrapy-0.1.3.dist-info/WHEEL
new_python_scrapy-0.1.3.dist-info/top_level.txt
new_python_scrapy-0.1.3.dist-info/RECORD
